<?xml version="1.0" encoding="UTF-8"?>
<window>
	<defaultcontrol always="true">570</defaultcontrol>
	<views>570</views>
	<controls>
		<include>DefaultBackground</include>
		<control type="grouplist" id="700">
			<include>OpenClose_Left</include>
			<orientation>vertical</orientation>
			<itemgap>-8.5</itemgap>
			<left>110</left>
			<top>162</top>
			<onup>700</onup>
			<ondown>700</ondown>
			<onleft>570</onleft>
			<onright>570</onright>
			<control type="togglebutton" id="4">
				<width>350</width>
				<height>199</height>
				<align>center</align>
				<aligny>top</aligny>
				<font>font12</font>
				<textoffsetx>20</textoffsetx>
				<textoffsety>130</textoffsety>
				<label>$LOCALIZE[31032]: $LOCALIZE[584]</label>
				<altlabel>$LOCALIZE[31032]: $LOCALIZE[585]</altlabel>
			</control>
			<control type="group" id="4100">
				<height>0</height>
				<control type="image">
					<top>-150</top>
					<width>350</width>
					<height>70</height>
					<aspectratio>keep</aspectratio>
					<texture>icons/order.png</texture>
				</control>
			</control>
			<include name="PlaylistWindowButton">
				<param name="control_id" value="21" />
				<param name="onclick" value="" />
				<param name="label" value="" />
				<param name="icon" value="icons/settings.png" />
			</include>
			<include name="PlaylistWindowButton">
				<param name="control_id" value="22" />
				<param name="onclick" value="" />
				<param name="label" value="$LOCALIZE[190]" />
				<param name="icon" value="icons/levels.png" />
			</include>
			<include name="PlaylistWindowButton">
				<param name="control_id" value="20" />
				<param name="onclick" value="" />
				<param name="label" value="$LOCALIZE[192]" />
				<param name="icon" value="DefaultIconError.png" />
			</include>
		</control>
		<control type="group">
			<left>250</left>
			<visible>Control.IsVisible(570)</visible>
			<include>OpenClose_Right</include>
			<control type="image">
				<left>210</left>
				<top>162</top>
				<width>1300</width>
				<height>746</height>
				<texture border="22">dialogs/dialog-bg.png</texture>
			</control>
			<control type="list" id="570">
				<left>230</left>
				<top>182</top>
				<width>1260</width>
				<height>700</height>
				<onleft>700</onleft>
				<onright>60</onright>
				<onup>570</onup>
				<ondown>570</ondown>
				<viewtype label="535">list</viewtype>
				<pagecontrol>60</pagecontrol>
				<scrolltime>200</scrolltime>
				<itemlayout height="100" width="1260">
					<control type="image">
						<left>0</left>
						<top>0</top>
						<width>1260</width>
						<height>100</height>
						<texture border="90,3,90,3">lists/separator.png</texture>
					</control>
					<control type="image">
						<left>5</left>
						<top>5</top>
						<width>90</width>
						<height>90</height>
						<texture border="4" fallback="DefaultAddon.png">$INFO[Listitem.Icon]</texture>
						<aspectratio>keep</aspectratio>
						<bordertexture colordiffuse="border_alpha">colors/black.png</bordertexture>
						<bordersize>4</bordersize>
					</control>
					<control type="label">
						<left>110</left>
						<top>0</top>
						<width>870</width>
						<height>50</height>
						<aligny>center</aligny>
						<label>[B]$INFO[ListItem.Label][/B]</label>
					</control>
					<control type="textbox">
						<left>110</left>
						<top>50</top>
						<width>870</width>
						<height>60</height>
						<font>font12</font>
						<textcolor>grey</textcolor>
						<label>$INFO[ListItem.Property(Event.Description)]</label>
					</control>
					<control type="label">
						<left>110</left>
						<top>0</top>
						<width>1120</width>
						<height>50</height>
						<font>font12</font>
						<textcolor>grey</textcolor>
						<align>right</align>
						<aligny>center</aligny>
						<label>$INFO[ListItem.Label2]</label>
					</control>
				</itemlayout>
				<focusedlayout height="100" width="1260">
					<control type="image">
						<left>0</left>
						<top>0</top>
						<width>1260</width>
						<height>100</height>
						<texture border="90,3,90,3">lists/separator.png</texture>
						<visible>!Control.HasFocus(570)</visible>
					</control>
					<control type="image">
						<left>0</left>
						<top>0</top>
						<width>1260</width>
						<height>100</height>
						<texture>lists/focus.png</texture>
						<visible>Control.HasFocus(570)</visible>
					</control>
					<control type="image">
						<left>5</left>
						<top>5</top>
						<width>90</width>
						<height>90</height>
						<texture border="4" fallback="DefaultAddon.png">$INFO[Listitem.Icon]</texture>
						<aspectratio>keep</aspectratio>
						<bordertexture colordiffuse="border_alpha">colors/black.png</bordertexture>
						<bordersize>4</bordersize>
					</control>
					<control type="label">
						<left>110</left>
						<top>0</top>
						<width>870</width>
						<height>50</height>
						<aligny>center</aligny>
						<label>[B]$INFO[ListItem.Label][/B]</label>
					</control>
					<control type="textbox">
						<left>110</left>
						<top>50</top>
						<width>870</width>
						<height>60</height>
						<font>font12</font>
						<textcolor>grey</textcolor>
						<label>$INFO[ListItem.Property(Event.Description)]</label>
					</control>
					<control type="label">
						<left>110</left>
						<top>0</top>
						<width>1120</width>
						<height>50</height>
						<font>font12</font>
						<textcolor>grey</textcolor>
						<align>right</align>
						<aligny>center</aligny>
						<label>$INFO[ListItem.Label2]</label>
					</control>
				</focusedlayout>
			</control>
			<include name="UpDownArrows">
				<param name="container_id" value="570" />
			</include>
			<control type="scrollbar" id="60">
				<right>210</right>
				<top>184</top>
				<width>12</width>
				<height>704</height>
				<onleft>570</onleft>
				<onright>2</onright>
				<orientation>vertical</orientation>
				<visible>Control.IsVisible(570)</visible>
			</control>
		</control>
		<control type="grouplist" id="9000">
			<left>-250</left>
			<top>110</top>
			<width>250</width>
			<height>600</height>
			<onleft>9000</onleft>
			<onright>570</onright>
			<onup>9000</onup>
			<ondown>9000</ondown>
			<onback>570</onback>
			<control type="label" id="200">
				<width>250</width>
				<height>35</height>
				<font>font12</font>
				<label>$LOCALIZE[14018]</label>
				<textcolor>button_focus</textcolor>
				<align>center</align>
				<aligny>center</aligny>
			</control>
			<control type="togglebutton" id="4">
				<description>Sort asc</description>
				<include>MediaMenuItemsCommon</include>
				<label>Sort: Descending</label>
				<altlabel>Sort: Ascending</altlabel>
				<usealttexture>Container.SortDirection(Ascending)</usealttexture>
			</control>
			<control type="label" id="201">
				<width>250</width>
				<height>35</height>
				<font>font12</font>
				<label>$LOCALIZE[31021]</label>
				<textcolor>button_focus</textcolor>
				<align>center</align>
				<aligny>center</aligny>
			</control>
			<control type="button" id="21">
				<description>Level button</description>
				<textwidth>235</textwidth>
				<include>MediaMenuItemsCommon</include>
				<label>-</label>
			</control>
			<control type="radiobutton" id="22">
				<description>Only show current level</description>
				<include>MediaMenuItemsCommon</include>
				<label>-</label>
			</control>
			<control type="button" id="20">
				<description>Clear button</description>
				<include>MediaMenuItemsCommon</include>
				<label>$LOCALIZE[192]</label>
			</control>
		</control>
		<include name="TopBar">
			<param name="breadcrumbs_label" value="Event log" />
			<param name="breadcrumbs_icon" value="icons/settings/video.png" />
		</include>
		<include>BottomBar</include>
	</controls>
</window>
