<?xml version="1.0" encoding="UTF-8"?>
<window>
    <defaultcontrol always="true">52</defaultcontrol>
    <allowoverlay>no</allowoverlay>
    <coordinates>
        <left>0</left>
        <top>0</top>
    </coordinates>
    <controls>
        <include>DefaultBackground</include>
        <control type="group">
            <include>OpenClose_Right</include>
            <control type="image">
                <description>LOGO</description>
                <left>615</left>
                <top>200</top>
                <width>690</width>
                <height>50</height>
                <aspectratio aligny="top" align="center">keep</aspectratio>
                <texture>icons/logo.png</texture>
            </control>
            <control type="label">
                <left>615</left>
                <top>300</top>
                <width>690</width>
                <height>40</height>
                <font>font13</font>
                <textcolor>grey2</textcolor>
                <align>center</align>
                <aligny>center</aligny>
                <label>$LOCALIZE[31421]</label>
            </control>
            <control type="list" id="52">
                <left>615</left>
                <top>370</top>
                <width>690</width>
                <height>401</height>
                <onleft>20</onleft>
                <onright>20</onright>
                <onup>20</onup>
                <ondown>20</ondown>
                <viewtype label="535">list</viewtype>
                <pagecontrol>60</pagecontrol>
                <scrolltime>200</scrolltime>
                <itemlayout height="130" width="690">
                    <control type="image">
                        <left>0</left>
                        <top>0</top>
                        <width>690</width>
                        <height>130</height>
                        <texture border="40">buttons/button-nofo.png</texture>
                    </control>
                    <control type="image">
                        <left>10</left>
                        <top>10</top>
                        <width>80</width>
                        <height>75</height>
                        <texture>$INFO[ListItem.Icon]</texture>
                        <aspectratio>keep</aspectratio>
                    </control>
                    <control type="label">
                        <left>110</left>
                        <top>10</top>
                        <width>580</width>
                        <height>60</height>
                        <font>font24_title</font>
                        <aligny>center</aligny>
                        <label>$INFO[ListItem.Label]</label>
                    </control>
                    <control type="label">
                        <left>110</left>
                        <top>50</top>
                        <width>580</width>
                        <height>50</height>
                        <font>font13</font>
                        <textcolor>grey</textcolor>
                        <aligny>center</aligny>
                        <label>$INFO[ListItem.Label2]</label>
                    </control>
                </itemlayout>
                <focusedlayout height="130" width="580">
                    <control type="image">
                        <left>0</left>
                        <top>0</top>
                        <width>690</width>
                        <height>130</height>
                        <texture border="40">buttons/button-nofo.png</texture>
                        <visible>!Control.HasFocus(52)</visible>
                    </control>
                    <control type="image">
                        <left>0</left>
                        <top>0</top>
                        <width>690</width>
                        <height>130</height>
                        <texture border="40">buttons/button-theme-fo.png</texture>
                        <visible>Control.HasFocus(52)</visible>
                    </control>
                    <control type="image">
                        <left>10</left>
                        <top>10</top>
                        <width>80</width>
                        <height>75</height>
                        <texture>$INFO[ListItem.Icon]</texture>
                        <aspectratio>keep</aspectratio>
                    </control>
                    <control type="label">
                        <left>110</left>
                        <top>10</top>
                        <width>580</width>
                        <height>60</height>
                        <font>font24_title</font>
                        <aligny>center</aligny>
                        <label>$INFO[ListItem.Label]</label>
                    </control>
                    <control type="label">
                        <left>110</left>
                        <top>50</top>
                        <width>580</width>
                        <height>50</height>
                        <font>font13</font>
                        <textcolor>grey</textcolor>
                        <aligny>center</aligny>
                        <label>$INFO[ListItem.Label2]</label>
                    </control>
                </focusedlayout>
            </control>
            <control type="button" id="20">
                <description>Power push button</description>
                <left>710</left>
                <top>950</top>
                <width>500</width>
                <height>85</height>
                <label>Power options</label>
                <font>font12</font>
                <align>center</align>
                <onclick>ActivateWindow(ShutdownMenu)</onclick>
                <onleft>52</onleft>
                <onright>52</onright>
                <onup>52</onup>
                <ondown>52</ondown>
                <colordiffuse>CCFFFFFF</colordiffuse>
            </control>
        </control>
    </controls>
</window>
